Metadata-Version: 1.1
Name: jupyter-c-kernel
Version: 1.2.2
Summary: Minimalistic C kernel for Jupyter
Home-page: https://github.com/brendanrius/jupyter-c-kernel/
Author: Brendan Rius
Author-email: ping@brendan-rius.com
License: UNKNOWN
Download-URL: https://github.com/brendanrius/jupyter-c-kernel/tarball/1.2.2
Keywords: jupyter,notebook,kernel,c
Platform: UNKNOWN
